ababltin.py
abaqusConstants.py
abaqusGui.py
abaqusTester.py
animation.py
annotationToolset.py
assembly.py
caeModules.py
caePrefsAccess.py
calibration.py
connector.py
connectorBehavior.py
customKernel.py
deleteObjectCallback.py
displayGroupMdbToolset.py
displayGroupOdbToolset.py
driverUtils.py
field.py
fields.py
inpParser.py
interaction.py
job.py
jobMessage.py
kernelAccess.py
load.py
material.py
mesh.py
meshEdit.py
methodCallback.py
monitorManager.py
odbAccess.py
odbConnectorBehavior.py
odbMaterial.py
odbSection.py
optimization.py
part.py
redentABQ.py
regionToolset.py
section.py
sketch.py
step.py
symbolicConstants.py
textRepr.py
upgradeScript.py
visualization.py
xyPlot.py
abaqus/_OptionsBase.py
abaqus/__init__.py
abaqus/builtin.py
abaqus/AbaqusCAEDisplayPreferences/CaeGuiPrefs.py
abaqus/AbaqusCAEDisplayPreferences/CaeKerPrefs.py
abaqus/AbaqusCAEDisplayPreferences/__init__.py
abaqus/AbaqusCAEDisplayPreferences/caePrefsAccess.py
abaqus/Adaptivity/AdaptiveMeshConstraint.py
abaqus/Adaptivity/AdaptiveMeshConstraintState.py
abaqus/Adaptivity/AdaptiveMeshControl.py
abaqus/Adaptivity/AdaptiveMeshDomain.py
abaqus/Adaptivity/AdaptivityIteration.py
abaqus/Adaptivity/AdaptivityModel.py
abaqus/Adaptivity/AdaptivityProcess.py
abaqus/Adaptivity/AdaptivityStep.py
abaqus/Adaptivity/DisplacementAdaptiveMeshConstraint.py
abaqus/Adaptivity/DisplacementAdaptiveMeshConstraintState.py
abaqus/Adaptivity/ErrorIndicatorResult.py
abaqus/Adaptivity/RemeshingRule.py
abaqus/Adaptivity/RuleResult.py
abaqus/Adaptivity/VelocityAdaptiveMeshConstraint.py
abaqus/Adaptivity/VelocityAdaptiveMeshConstraintState.py
abaqus/Adaptivity/__init__.py
abaqus/Amplitude/ActuatorAmplitude.py
abaqus/Amplitude/Amplitude.py
abaqus/Amplitude/AmplitudeModel.py
abaqus/Amplitude/AmplitudeOdb.py
abaqus/Amplitude/BaselineCorrection.py
abaqus/Amplitude/Correlation.py
abaqus/Amplitude/DecayAmplitude.py
abaqus/Amplitude/EquallySpacedAmplitude.py
abaqus/Amplitude/ModulatedAmplitude.py
abaqus/Amplitude/PeriodicAmplitude.py
abqpy-2025.8.dist-info/LICENSE
abqpy-2025.8.dist-info/METADATA
abqpy-2025.8.dist-info/WHEEL
abqpy-2025.8.dist-info/entry_points.txt
abqpy-2025.8.dist-info/top_level.txt
abqpy-2025.8.dist-info/RECORD
