Metadata-Version: 2.2
Name: abqpy
Version: 2025.8
Summary: Type hints for Abaqus/Python scripting
Author-email: WANG Hailin <hailin.wang@connect.polyu.hk>
Project-URL: Homepage, https://abqpy.com
Project-URL: GitHub, https://github.com/haiiliin/abqpy
Project-URL: Bug Tracker, https://github.com/haiiliin/abqpy/issues
Project-URL: Read the Docs, https://readthedocs.org/projects/abqpy
Project-URL: Documentation, https://haiiliin.github.io/abqpy/
Classifier: Programming Language :: Python
Classifier: Programming Language :: Python :: 3
Classifier: Programming Language :: Python :: 3.8
Classifier: Programming Language :: Python :: 3.9
Classifier: Programming Language :: Python :: 3.10
Classifier: Programming Language :: Python :: 3.11
Classifier: Programming Language :: Python :: 3.12
Classifier: Programming Language :: Python :: 3.13
Classifier: Programming Language :: Python :: Implementation :: PyPy
Classifier: License :: OSI Approved :: MIT License
Classifier: Operating System :: OS Independent
Requires-Python: >=3.8
License-File: LICENSE
Requires-Dist: auto-all
Requires-Dist: fire
Requires-Dist: pydantic
Requires-Dist: typeguard
Requires-Dist: typing-extensions
Provides-Extra: jupyter
Requires-Dist: ipynbname; extra == "jupyter"
Requires-Dist: nbconvert; extra == "jupyter"
